{
  
  "animal_auction": "Animal Auction",
  "search_animals": "Search Animals",
  "search_by": "Search By",
  "search_by_title_description_location": "Search by title, description, location",
  "filter_by": "Filter By",
  "all_categories": "All Categories",
  "cows": "Cows",
  "buffaloes": "Buffaloes",
  "goats": "Goats",
  "sheep": "Sheep",
  "poultry": "Poultry",
  "horses": "Horses",
  "sort_by": "Sort By",
  "latest_first": "Latest First",
  "price_low_to_high": "Price Low to High",
  "price_high_to_low": "Price High to Low",
  "apply_filters": "Apply Filters",
  "post_your_animal": "Post Your Animal",
  "select_animal": "Select Animal",
  "choose_animal_category": "Choose Animal Category",
  "type_manually": "Type Manually",
  "type_animal_name": "Type animal name",
  "animal_age": "Animal Age",
  "optional": "Optional",
  "animal_age_placeholder": "Enter animal age",
  "breed": "Breed",
  "breed_placeholder": "Enter breed",
  "weight_kg": "Weight (kg)",
  "price": "Price",
  "description": "Description",
  "description_placeholder": "Describe your animal",
  "location": "Location",
  "location_placeholder": "Enter location",
  "upload_photos": "Upload Photos",
  "contact_number": "Contact Number",
  "enter_10_digit_number": "Enter 10 digit number",
  "post_animal": "Post Animal",
  "available_animals": "Available Animals",
  "age": "Age",
  "years": "years",
  "weight": "Weight",
  "call_seller": "Call Seller",
  "english": "English",
  "hindi": "Hindi",
  "telugu": "Telugu",
  "dashboard": "Dashboard",
  "search_jobs": "Search Jobs",
  "back_to_dashboard": "Back to Dashboard",
  "post_job": "Post a Job",
  "liked_jobs": "Liked Jobs",
  "select_filter": "Select Filter",
  "salary": "Salary",
  "job_title": "Job Title",
  "job_location": "Job Location",
  "date_posted": "Date Posted",
  "job_type": "Job Type",
  "min_salary": "Min Salary",
  "enter_minimum_salary": "Enter minimum salary",
  "max_salary": "Max Salary",
  "enter_maximum_salary": "Enter maximum salary",
  "select_sort": "Select Sort",
  "high_to_low_salary": "High to Low Salary",
  "low_to_high_salary": "Low to High Salary",
  "select_job": "Select Job",
  "enter_location": "Enter location",
  "select_date": "Select Date",
  "last_1_day": "Last 1 Day",
  "last_7_days": "Last 7 Days",
  "last_30_days": "Last 30 Days",
  "select_job_type": "Select Job Type",
  "full_time": "Full Time",
  "part_time": "Part Time",
  "contract": "Contract",
  "reset_search": "Reset Search",
  "job_description": "Job Description",
  "not_specified": "Not specified",
  "posted_by": "Posted By",
  "profile_picture": "Profile Picture",
  "posted_on": "Posted On",
  "view_on_map": "View on Map",
  "hello_interested_in_job": "Hello, I am interested in your job posting:",
  "contact_on_whatsapp": "Contact on WhatsApp",
  "contact_via_sms": "Contact via SMS",
  "no_jobs_found": "No jobs found",
  "saved_animals": "Saved Animals",
  "min_price": "Min Price",
  "enter_min_price": "Enter minimum price",
  "max_price": "Max Price",
  "enter_max_price": "Enter maximum price",
  "select_category": "Select Category",
  "tap_photo_to_view": "Tap photo to view",
  "interested_in_animal": "Hello, I am interested in your animal:",
  "saved_on": "Saved On",
  "no_saved_animals": "No saved animals"
}
